fastapi_keycloak_middleware/__init__.py
fastapi_keycloak_middleware/decorators/__init__.py
fastapi_keycloak_middleware/decorators/require_permission.py
fastapi_keycloak_middleware/decorators/strip_request.py
fastapi_keycloak_middleware/dependencies/__init__.py
fastapi_keycloak_middleware/dependencies/check_permission.py
fastapi_keycloak_middleware/dependencies/get_auth.py
fastapi_keycloak_middleware/dependencies/get_authorization_result.py
fastapi_keycloak_middleware/dependencies/get_user.py
fastapi_keycloak_middleware/exceptions.py
fastapi_keycloak_middleware/fast_api_user.py
fastapi_keycloak_middleware/keycloak_backend.py
fastapi_keycloak_middleware/middleware.py
fastapi_keycloak_middleware/schemas/__init__.py
fastapi_keycloak_middleware/schemas/authorization_methods.py
fastapi_keycloak_middleware/schemas/authorization_result.py
fastapi_keycloak_middleware/schemas/exception_response.py
fastapi_keycloak_middleware/schemas/keycloak_configuration.py
fastapi_keycloak_middleware/schemas/match_strategy.py
fastapi_keycloak_middleware/setup.py
fastapi_keycloak_middleware-1.5.0.dist-info/METADATA
fastapi_keycloak_middleware-1.5.0.dist-info/WHEEL
fastapi_keycloak_middleware-1.5.0.dist-info/LICENSE
fastapi_keycloak_middleware-1.5.0.dist-info/RECORD
