Metadata-Version: 2.1
Name: fastapi-keycloak-middleware
Version: 1.5.0
Summary: Middleware for FastAPI to authenticate a user against keycloak
Author: Daniel Herrmann
Author-email: daniel.herrmann1@gmail.com
Requires-Python: >=3.11,<4
Classifier: Programming Language :: Python :: 3
Classifier: Programming Language :: Python :: 3.11
Requires-Dist: fastapi (>=0.73.0)
Requires-Dist: python-keycloak (>=4,<5,>=4.1,>=7.0.1)
